dprint/__init__.py
dprint/_impl.py
dprint-0.1.0.dist-info/LICENSE
dprint-0.1.0.dist-info/WHEEL
dprint-0.1.0.dist-info/METADATA
dprint-0.1.0.dist-info/RECORD
