Metadata-Version: 2.1
Name: dprint
Version: 0.1.0
Summary: A printing debugging helper.
Home-page: https://github.com/pradyunsg/dprint
License: UNKNOWN
Author: Pradyun Gedam
Author-email: pradyunsg@gmail.com
Classifier: License :: OSI Approved :: MIT License
